django_zendesk/__init__.py
django_zendesk/models.py
django_zendesk/test_urls.py
django_zendesk/tests.py
django_zendesk/views.py
pivotal_django_zendesk-1.1.0.dist-info/LICENSE.txt
pivotal_django_zendesk-1.1.0.dist-info/METADATA
pivotal_django_zendesk-1.1.0.dist-info/WHEEL
pivotal_django_zendesk-1.1.0.dist-info/top_level.txt
pivotal_django_zendesk-1.1.0.dist-info/RECORD
