Metadata-Version: 2.1
Name: pivotal-django-zendesk
Version: 1.1.0
Summary: Provides single-sign on functionality between a django.contrib.auth based site and Zendesk
Home-page: https://github.com/pivotal-energy-solutions/django_zendesk
Author: Pivotal Energy Solutions
Author-email: sklass@pivotalenergysolutions.com
License: UNKNOWN
Download-URL: https://github.com/pivotal-energy-solutions/django_zendesk/archive/1.1.0.tar.gz
Project-URL: Bug Reports, https://github.com/pivotal-energy-solutions/django_zendesk/issues
Project-URL: Say Thanks!, https://saythanks.io/to/rh0dium
Project-URL: Original Source, https://bitbucket.org/jonknee/django_zendesk
Keywords: django zendesk authentication
Platform: UNKNOWN
Classifier: Development Status :: 5 - Production/Stable
Classifier: Environment :: Web Environment
Classifier: Framework :: Django
Classifier: License :: OSI Approved :: Apache Software License
Classifier: Programming Language :: Python :: 2
Classifier: Programming Language :: Python :: 2.7
Classifier: Topic :: Internet :: WWW/HTTP
Classifier: Topic :: Internet :: WWW/HTTP :: Dynamic Content
Classifier: Topic :: Software Development :: Libraries :: Python Modules
Requires-Dist: django (<2,>=1.11)
